[
    {
        "mnemonic": "aesdeclast",
        "mnemonicPrecise": "aesdeclastx",
        "opcode": 997599,
        "opcodeHex": "F38DF",
        "operands": [
            "RegisterXmm",
            [
                "RegisterXmm",
                "Memory"
            ]
        ],
        "operandSize": 128,
        "operandEncoding": "rm",
        "extraPrefixes": [
            102
        ],
        "modes": [
            "REAL",
            "PROT",
            "COMP",
            "LEG",
            "X32",
            "X64"
        ],
        "extensions": [
            "AES"
        ]
    }
]